Workbook

Sheet CALCULAR CUOTAS
B1: PASOS PARA USO DEL SIMULADOR: 1.- Digite el saldo en mora. 2.- Seleccione el % del pago inicial (Ver tabla de Rangos). 3.- Seleccione el número de cuotas (Ver tabla de Rangos). 4.- Verifique que la fecha de la solicitud sea la del día de hoy. | E1: TABLA DE RANGOS PARA ACUERDOS DE PAGOS
E2: SALDO EN MORA | F2: CUOTA INICIAL MÍNIMA | G2: DÍAS HÁBILES PARA PAGO CUOTA INICIAL | H2: CANTIDAD MAX. DE CUOTAS PARA ACUERDO (EN QUINCENAS) | I2: PLAZO MAXIMO EN MESES | J2: AUTORIZACION | N2: 0.3 | O2: 1
E3: Entre $50.001= y $100.000= | F3: 0.3 | G3: 2 | H3: 2 | I3: 1 | J3: CALL CENTER, CAV´s Y PQR´s | N3: 0.4 | O3: 2
B4: Saldo en mora | N4: 0.5 | O4: 3
B5: % del Pago inicial | E5: Entre $100.001= y $500.000= | F5: 0.3 | G5: 2 | H5: 4 | I5: 2 | J5: CALL CENTER, CAV´s Y PQR´s | N5: 0.6 | O5: 4
B6: Valor cuota inicial (pagar en 2 días Hábiles) | C6: =C4*C5 -> 0 | N6: 0.7 | O6: 5
B7: Valor a diferir en cuotas | C7: =C4-C6 -> 0 | E7: Entre $500.001= y $2.000.000= | F7: 0.4 | G7: 2 | H7: 6 | I7: 3 | J7: CALL CENTER, CAV´s Y PQR´s | N7: 0.8 | O7: 6
B8: Número de cuotas a pactar: | N8: 0.9
B9: Valor de cuotas | C9: =C7/C8 -> #DIV/0! | E9: Superior a $2.000.001 | F9: 0.4 | G9: 5 o 15 | H9: 12 | I9: 6 | J9: ÁREA DE COBRANZA | N9: 1
B13: FECHAS PARA PAGOS DE CUOTAS | E13: NOTA: Luego de calcular las cuotas y fechas dirígete a Tickler, el cual debe estar diligenciado.
B14: FECHA DE LA SOLICITUD (HOY) | C14: =NOW() -> 43698.549
B15: Fecha de primera cuota | C15: =C14+15 -> 43713.549
B16: Fecha de Segunda Cuota | C16: =C15+15 -> 43728.549
B17: Fecha de Tercera cuota | C17: =C16+15 -> 43743.549
B18: Fecha de Cuarta cuota | C18: =C17+15 -> 43758.549
B19: Fecha de Quinta Cuota | C19: =C18+15 -> 43773.549
B20: Fecha de Sexta Cuota | C20: =C19+15 -> 43788.549
B21: Nota: Seleccione las fechas hasta el número de cuotas pactadas

Sheet TICKLER
B3: RECUERDA: | C3: El tickler ACUERDOP desaparece. Tu labor requiere de la creación de un tickler COD_INFO con la siguiente información:
C5: DESCRIPCIÓN CORTA: | D5: INF. ACUERDO DE PAGO. | M5: A INICIO
C6: DESCRIPCIÓN LARGA:
C7: Acuerdo de pago APROBADO y con servicio activo, (Debe pagar los CFM en la FLP durante la vigencia del acuerdop):
C9: Fecha de la solicitud | D9: ='CALCULAR CUOTAS'!C14 -> 43698.549 | E9: SALDO: | F9: ='CALCULAR CUOTAS'!C4 -> 0
C10: Pago inicial: | D10: ='CALCULAR CUOTAS'!C6 -> 0 | E10: (Pagar en los siguientes 2 días hábiles.)
C11: 1° CUOTA | D11: ='CALCULAR CUOTAS'!$C$9 -> #DIV/0! | E11: FECHA DE PAGO: | F11: ='CALCULAR CUOTAS'!C15 -> 43713.549
C12: 2°CUOTA | D12: ='CALCULAR CUOTAS'!$C$9 -> #DIV/0! | E12: FECHA DE PAGO: | F12: ='CALCULAR CUOTAS'!C16 -> 43728.549
C13: 3°CUOTA | D13: ='CALCULAR CUOTAS'!$C$9 -> #DIV/0! | E13: FECHA DE PAGO: | F13: ='CALCULAR CUOTAS'!C17 -> 43743.549
C14: 4° CUOTA | D14: ='CALCULAR CUOTAS'!$C$9 -> #DIV/0! | E14: FECHA DE PAGO: | F14: ='CALCULAR CUOTAS'!C18 -> 43758.549
C15: 5° CUOTA | D15: ='CALCULAR CUOTAS'!$C$9 -> #DIV/0! | E15: FECHA DE PAGO: | F15: ='CALCULAR CUOTAS'!C19 -> 43773.549
C16: 6° CUOTA | D16: ='CALCULAR CUOTAS'!$C$9 -> #DIV/0! | E16: FECHA DE PAGO: | F16: ='CALCULAR CUOTAS'!C20 -> 43788.549
C17: CONDICIONES:
C18: 1.- Debe cancelar las facturas que se generen dentro de las fechas límites de pago mientras dure el acuerdo independientemente de las cuotas de este.
C19: 2.- El acuerdo no exime de reportes ante centrales de riesgo ni cobro de intereses de mora.
C20: 3.-El incumplimiento de cualquiera de los puntos anula el presente acuerdo.
C21: 4.- En caso de aceptar las condiciones se retira la gestión de cobranza de abogado externo.
C22: 5.- A partir de la fecha se verifica durante dos días hábiles el ingreso del primer pago.
C23: 6.-Si no ingresa el pago inicial o éste se realiza por menor valor, se entiende como no aceptado el presente acuerdo.
C24: 7.-Después de cancelada la cuota inicial, el saldo restante deberá ser cancelado en las fechas establecidas dentro del acuerdo.
C25: 8.- Puede hacer uso de cualquiera de nuestros canales hábilitados para pagos, pero se le recomienda usar preferiblemente medio de pago de cajas directas de claro.
C26: 9.- El incumplimiento de alguna de las cuotas o cargos fijos mensuales acarreará la suspensión del servicio y se constituirá incumplimiento del acuerdo.
